gpt_scientist/__init__.py
gpt_scientist/config.py
gpt_scientist/google_doc_parser.py
gpt_scientist/model_pricing.json
gpt_scientist/scientist.py
gpt_scientist/stats.py
gpt_scientist/utils.py
gpt_scientist/llm/__init__.py
gpt_scientist/llm/client.py
gpt_scientist/llm/prompts.py
gpt_scientist/processors/__init__.py
gpt_scientist/processors/core.py
gpt_scientist/processors/csv.py
gpt_scientist/processors/sheets.py
gpt_scientist/processors/workers.py
gpt_scientist/verification/__init__.py
gpt_scientist/verification/quotes.py
gpt_scientist-0.1.33.dist-info/licenses/LICENSE
gpt_scientist-0.1.33.dist-info/METADATA
gpt_scientist-0.1.33.dist-info/WHEEL
gpt_scientist-0.1.33.dist-info/top_level.txt
gpt_scientist-0.1.33.dist-info/RECORD
