Metadata-Version: 2.4
Name: gpt_scientist
Version: 0.1.33
Summary: A library for processing textual datasets with large language models.
Author-email: Nadia Polikarpova <nadia.polikarpova@gmail.com>
License: MIT license
Project-URL: homepage, https://github.com/nadia-polikarpova/gpt-scientist
License-File: LICENSE
Requires-Dist: pandas
Requires-Dist: openai>=1.99.0
Requires-Dist: fuzzysearch
Requires-Dist: tenacity
Requires-Dist: pydantic
Requires-Dist: requests
Requires-Dist: nest_asyncio
Dynamic: license-file
